call_viz/__init__.py
call_viz/core.py
call_viz/node.py
call_viz/tree.py
call_viz-0.1.0.dist-info/LICENSE
call_viz-0.1.0.dist-info/METADATA
call_viz-0.1.0.dist-info/WHEEL
call_viz-0.1.0.dist-info/top_level.txt
call_viz-0.1.0.dist-info/RECORD
