Metadata-Version: 2.1
Name: call_viz
Version: 0.1.0
Summary: Recursive function calls visualization using Graphviz
Home-page: https://github.com/theobori/call_viz
Author: Théo Bori
Author-email: nagi@tilde.team
License: MIT License
License-File: LICENSE
Requires-Dist: graphviz
